{
  "erase": "Απαλοιφή",
  "inputFeaturesSectionText": "Επιλέξτε το θεματικό επίπεδο εισόδου και το θεματικό επίπεδο επικάλυψης που περιέχει τα στοιχεία τα οποία θέλετε να υπερθέσετε.",
  "intersect": "Τομή",
  "itemProperties": {
    "description": "Το feature layer που δημιουργείται από την εκτέλεση το εργαλείο ανάλυσης \"Υπέρθεση θεματικών επιπέδων\".",
    "snippet": "Το feature layer που δημιουργείται από την Υπέρθεση θεματικών επιπέδων"
  },
  "outputType": "Γεωμετρία εξόδου",
  "overlayLayer": "Υπέρθεση στοιχείων",
  "overlaySettingsSectionLabel": "Ρυθμίσεις υπέρθεσης",
  "overlaySettingsSectionText": "Προσδιορίστε την επιθυμητή χωρική αλληλεπίδραση μεταξύ των στοιχείων εισόδου και υπέρθεσης.",
  "overlayType": "Τύπος υπέρθεσης",
  "sameAsInput": "Ίδιο με τα στοιχεία εισόδου",
  "union": "Ένωση"
}
