{
  "calculationInterval": "Interval de calculare mediu",
  "differenceFromMean": "Diferență față de medie",
  "differenceFromMedian": "Diferență față de mediană",
  "externalRaster": "Raster de referință",
  "inputMultidimensionalRaster": "Strat tematic de imagini multidimensionale",
  "itemProperties": {
    "description": "Rezultatul generat din executarea instrumentului de analiză Generare anomalie multidimensională.",
    "snippet": "Rezultatul generat din Generare anomalie multidimensională"
  },
  "method": "Metoda de calculare a anomaliilor",
  "percentDifferenceFromMean": "Diferență procentuală față de medie",
  "percentDifferenceFromMedian": "Diferență procentuală față de mediană",
  "percentOfMean": "Procentajul mediei",
  "percentOfMedian": "Procentajul medianei",
  "referenceMeanRaster": "Raster de referință",
  "settingsGroupLabel": "Setări anormale",
  "variables": "Variabile [informații dimensiuni] (descriere)",
  "zScore": "Scorul Z"
}
