{
  "FOAnalysisSettingGroupLabel": "Ustawienia elementów odstających",
  "inputFeaturesSectionText": "Wybierz warstwę zawierającą obiekty, na których należy wykonać analizę elementów odstających.",
  "itemProperties": {
    "description": "Warstwa obiektowa wygenerowana w wyniku uruchomienia narzędzia analizy Znajdź elementy odstające.",
    "snippet": "Warstwa obiektowa wygenerowana w wyniku uruchomienia narzędzia Znajdź elementy odstające"
  },
  "optimizationGroupLabel": "Ustawienia optymalizacji",
  "toolName": "Znajdź elementy odstające"
}
