{
  "d8": "D8",
  "flowDirectionTypeLabel": "Akış doğrultusu türü",
  "forceFlowLabel": "Kenar hücrelerini dışarı doğru akışa zorla",
  "inputDepressionsDataLabel": "Girdi çöküntü rasterı veya detayları",
  "inputLayersGroupText": "Girdi yüzeyi rasterını ve isteğe bağlı olarak çöküntü verilerini ve ağırlık rasterını seçin.",
  "inputSurfaceRasterLabel": "Girdi yüzey rasterı",
  "inputWeightRasterLabel": "Girdi biriktirme ağırlık rasterı",
  "itemProperties": {
    "description": "Çıktı, Sürekli Akış Türet analiz aracı kullanılarak oluşturuldu.",
    "snippet": "Çıktı, Sürekli Akış Türet ile oluşturuldu"
  },
  "mfd": "MFD",
  "outputFlowAccumulationRasterLabel": "Akış birikim rasterı çıktı adı",
  "outputFlowDirectionRasterLabel": "Çıktı akış doğrultusu rasterı adı"
}
