{
  "d8": "D8",
  "flowDirectionTypeLabel": "Flow direction type",
  "forceFlowLabel": "Force edge cells to flow outwards",
  "inputDepressionsDataLabel": "Input depressions raster or features",
  "inputLayersGroupText": "Choose the input surface raster, and optionally the depression data and the weight raster.",
  "inputSurfaceRasterLabel": "Input surface raster",
  "inputWeightRasterLabel": "Input accumulation weight raster",
  "itemProperties": {
    "description": "Output generated from running the Derive Continuous Flow analysis tool.",
    "snippet": "Output generated from Derive Continuous Flow"
  },
  "mfd": "MFD",
  "outputFlowAccumulationRasterLabel": "Output flow accumulation raster name",
  "outputFlowDirectionRasterLabel": "Output flow direction raster name"
}
