{
  "toolName": "Watershed",
  "version": "0.1.0",
  "rules": [
    {
      "ruleType": "set",
      "value": "$[Component].inPourPointRasterOrFeatures.selectedLayers",
      "destination": "pourPointField",
      "property": "mapLayer"
    },
    {
      "ruleType": "expression",
      "expression": "($[Component].inPourPointRasterOrFeatures.selectedLayers.type.length > 0) AND ($[Component].inPourPointRasterOrFeatures.selectedLayers.type NOT 'feature')",
      "destination": "pourPointField",
      "effectParams": {
        "fieldTypes": ["integer", "small-integer", "single", "double"]
      }
    },
    {
      "ruleType": "expression",
      "expression": "(($[Component].inPourPointRasterOrFeatures.selectedLayers.type.length > 0) AND ($[Component].inPourPointRasterOrFeatures.selectedLayers.type NOT 'feature')) AND ($[Component].inPourPointRasterOrFeatures.processedLayerProperties.rasterInfo.attributeTable = NULL)",
      "destination": "pourPointField",
      "effectParams": {
        "readOnly": true,
        "value": "Value"
      }
    },
    {
      "ruleType": "expression",
      "expression": "(($[Component].inputFlowDirectionRaster.user.portal NOT undefined) AND ($[Component].inputFlowDirectionRaster.user.portal.isPortal = true))",
      "destination": "resultType",
      "effectParams": {
        "value": "DYNAMIC_IMAGERY_LAYER",
        "visible": false
      }
    },
    {
      "ruleType": "expression",
      "expression": "(('portal:publisher:publishDynamicImagery' IN $[Component].inputFlowDirectionRaster.user.privileges) AND ('portal:publisher:publishTiledImagery' NOT IN $[Component].inputFlowDirectionRaster.user.privileges))",
      "destination": "resultType",
      "effectParams": {
        "choiceList": ["DYNAMIC_IMAGERY_LAYER"],
        "choiceListIcons": {
          "DYNAMIC_IMAGERY_LAYER": "image-layer"
        },
        "choiceListLabels": {
          "DYNAMIC_IMAGERY_LAYER": "$dynamicImageryLayer"
        },
        "value": "DYNAMIC_IMAGERY_LAYER"
      }
    },
    {
      "ruleType": "expression",
      "expression": "(('portal:publisher:publishDynamicImagery' NOT IN $[Component].inputFlowDirectionRaster.user.privileges) AND ('portal:publisher:publishTiledImagery' IN $[Component].inputFlowDirectionRaster.user.privileges))",
      "destination": "resultType",
      "effectParams": {
        "choiceListIcons": {
          "TILED_IMAGERY_LAYER": "tiled-imagery-layer"
        },
        "choiceListLabels": {
          "TILED_IMAGERY_LAYER": "$tiledImageryLayer"
        },
        "value": "TILED_IMAGERY_LAYER"
      }
    }
  ],
  "environmentSettings": {
    "raster": ["snapRaster", "cellSize", "mask", "parallelProcessingFactor"]
  },
  "UIparameters": [
    {
      "label": "$inputLayersGroupLabel",
      "componentName": "analysis-block",
      "summaryText": "$inputLayersGroupText",
      "UIparameters": [
        {
          "name": "inputFlowDirectionRaster",
          "label": "$inputFlowDirectionRasterLabel",
          "componentName": "analysis-layer-input",
          "required": true,
          "selectionMode": "single",
          "hideSketch": true,
          "layerFilterType": ["imagery_float", "imagery_integer"]
        },
        {
          "label": "$inPourPointRasterOrFeaturesLabel",
          "name": "inPourPointRasterOrFeatures",
          "componentName": "analysis-layer-input",
          "required": true,
          "selectionMode": "single",
          "hideSketch": false,
          "layerFilterType": ["feature", "imagery_float", "imagery_integer"]
        },
        {
          "name": "pourPointField",
          "label": "$pourPointFieldLabel",
          "componentName": "analysis-field-input",
          "required": false,
          "showFieldInfo": true,
          "selectionMode": "single",
          "fieldTypes": ["oid", "integer", "small-integer", "single", "double"],
          "useDefaultValue": true,
          "readOnly": false
        }
      ]
    },
    {
      "label": "$resultLayersGroupLabel",
      "componentName": "analysis-block",
      "summaryText": "$resultLayersGroupText",
      "UIparameters": [
        {
          "name": "outputName",
          "label": "$outputRasterNameLabel",
          "placeholderText": "$outputNamePlaceholderText",
          "componentName": "analysis-string-input",
          "required": true
        },
        {
          "name": "resultType",
          "label": "$resultType",
          "componentName": "analysis-string-input",
          "choiceList": ["TILED_IMAGERY_LAYER", "DYNAMIC_IMAGERY_LAYER"],
          "choiceListIcons": {
            "TILED_IMAGERY_LAYER": "tiled-imagery-layer",
            "DYNAMIC_IMAGERY_LAYER": "image-layer"
          },
          "choiceListLabels": {
            "TILED_IMAGERY_LAYER": "$tiledImageryLayer",
            "DYNAMIC_IMAGERY_LAYER": "$dynamicImageryLayer"
          },
          "value": "TILED_IMAGERY_LAYER"
        },
        {
          "name": "saveResultIn",
          "label": "$saveResultIn",
          "componentName": "analysis-folder-input"
        }
      ]
    }
  ]
}
