{
  "fromSourceLabel": "Deplasare de la sursă",
  "horizontalFactorLabel": "Factor orizontal",
  "horizontalFactorSectionLabel": "Mișcare orizontală",
  "inputBarrierRasterOrFeaturesLabel": "Intrare raster barieră sau obiecte spațiale",
  "inputCostRasterLabel": "Intrare raster costuri",
  "inputDistanceSettingsGroupLabel": "Setări de distanță",
  "inputDistanceSettingsGroupText": "Selectați metoda de calculare a distanței. Definiți mișcarea verticală și orizontală. Definiți caracteristicile sursei.",
  "inputHorizontalRasterLabel": "Intrare taster orizontal",
  "inputLayersGroupText": "Alegeți stratul tematic de intrare care conține surse, bariere, suprafețe și valori de costuri.",
  "inputSourceField": "Intrare câmp sursă",
  "inputSourceRasterOrFeaturesLabel": "Intrare raster sursă sau obiecte spațiale",
  "inputSurfaceRasterLabel": "Intrare raster suprafață",
  "inputVerticalRasterLabel": "Intrare raster vertical",
  "itemProperties": {
    "description": "Rezultatul generat prin executarea instrumentului de analiză Alocare distanță.",
    "snippet": "Rezultat generat din Alocarea distanței"
  },
  "outputBackDirectionRasterNameLabel": "Nume raster de direcție inversă rezultat",
  "outputDistanceAccumulationRasterNameLabel": "Nume raster acumulare distanță rezultat",
  "outputDistanceAllocationRasterNameLabel": "Nume raster alocare distanță rezultat",
  "outputSourceDirectionRasterNameLabel": "Nume raster de direcție sursă rezultat",
  "outputSourceLocationRasterNameLabel": "Nume raster de locație sursă rezultat",
  "sourceCostMultiplierLabel": "Multiplicator cost",
  "sourceDirectionLabel": "Direcție de deplasare",
  "sourceInitialAccumulationLabel": "Acumulare inițială",
  "sourceMaximumAccumulationLabel": "Acumulare maximă",
  "sourceSectionLabel": "Caracteristici sursă ",
  "toSourceLabel": "Deplasare către sursă",
  "type": "Tip",
  "verticalFactorLabel": "Factor vertical",
  "verticalFactorSectionLabel": "Mișcare verticală"
}
