{
  "aspect": "Hellingsretning",
  "biquadratic": "Bikvadratisk",
  "casorati_curvature": "Casorati-kurvatur",
  "centimeter": "Centimeter",
  "contour_curvature": "Plan (projisert kontur) kurvatur",
  "contour_geodesic_torsion": "Kontur geodetisk torsjon",
  "decimal_degrees": "Desimalgrader",
  "decimeter": "Desimeter",
  "degreeLabel": "Grad",
  "distanceUnit": "Enhet",
  "foot": "Fot",
  "gaussian_curvature": "Gauss-kurvatur",
  "inch": "Tomme",
  "inputLayersGroupText": "Velg det innlagte overflaterasteret.",
  "inputSurfaceParamSettingsGroupLabel": "Innstillinger for overflateparameter",
  "inputSurfaceParamSettingsGroupText": "Angi typen overflateparameter og tilknyttede parametere. Definer størrelsen på nabolaget og om størrelsen skal tilpasses til terrenget.",
  "inputSurfaceRasterLabel": "Innlagt overflateraster",
  "itemProperties": {
    "description": "Resultat generert ved kjøring av analyseverktøyet Overflateparameter.",
    "snippet": "Resultat generert fra Overflateparameter"
  },
  "kilometer": "Kilometer",
  "localSurfaceTypeLabel": "Lokal overflatetype",
  "mean_curvature": "Gjennomsnittlig kurvatur",
  "meter": "Meter",
  "mile_US": "Amerikansk mile",
  "milimeter": "Millimeter",
  "nautical_mile": "Nautisk mil",
  "neighborhoodDistanceLabel": "Nabolagsavstand",
  "outputSlopeMeasurementLabel": "Måling av helling",
  "parameterTypeLabel": "Parametertype",
  "percentRiseLabel": "Prosent stigning",
  "profile_curvature": "Profil (normal hellingslinje) kurvatur",
  "projectGeodesicAzimuthsLabel": "Projiser geodetiske asimutter",
  "quadratic": "Kvadratisk",
  "slope": "Helling",
  "tangential_curvature": "Tangentiell (normal kontur) kurvatur",
  "useAdaptiveNeighborhoodLabel": "Bruk adaptivt nabolag",
  "useEquatorialAspectLabel": "Bruk ekvatorialaspekt",
  "yard": "Yard",
  "zUnitLabel": "Z-enhet"
}
