{
  "FSLGroupLabel": "Configuración de búsqueda de similitud",
  "FSLGroupSectionText": "Defina los criterios para evaluar la similitud y especificar el número de resultados devueltos.",
  "candidateFieldLabel": "Campo desde capa candidata",
  "inputFeaturesSectionText": "Elija capas para calcular las clasificaciones de similitud.",
  "inputLayerLabel": "Capa de ubicaciones de referencia",
  "itemProperties": {
    "description": "Capa de entidades generada al ejecutar la herramienta de análisis Buscar ubicaciones similares.",
    "snippet": "Capa de entidades generada de Buscar ubicaciones similares"
  },
  "matchingFieldsLabels": "Criterios de selección",
  "numberOfResultsLabel": "Número de ubicaciones devueltas",
  "referenceFieldLabel": "Campo desde capa de referencia",
  "returnAllLabel": "Devolver todos los resultados",
  "searchLayerLabel": "Buscar capa candidata",
  "toolName": "Buscar ubicaciones similares",
  "valueTableAccordion": "Criterios de búsqueda"
}
