{
  "classValueField": "Klasės reikšmės laukas",
  "confidenceScoreField": "Patikimumo verčių laukas",
  "detectObjectsInputSectionText": "Pasirinkite vaizdų sluoksnį arba elementų sluoksnį su vaizdo priedais.",
  "detectObjectsResultSectionText": "Išvesties elementų sluoksnis su aptiktais elementais.",
  "inputRaster": "Įvesties vaizdų sluoksnis arba elementų sluoksnis",
  "itemProperties": {
    "description": "Išvestis sugeneruota paleidus analizės įrankį Aptikti objektus naudojant gilųjį mokymąsi.",
    "snippet": "Išvestis sugeneruota naudojant Aptikti objektus naudojant gilųjį mokymąsi"
  },
  "maxOverlapRatio": "Didžiausio persidengimo santykis",
  "model": "Objektų aptikimo modelis",
  "modelArguments": "Modelio argumentai",
  "modelLabel": "Pasirinkti modelį",
  "processAllRasterItems": "Apdorojimo režimas",
  "processAsMosaickedImage": "Apdoroti kaip mozaikinį vaizdą",
  "processItemsSeparately": "Visus rastro elementus apdoroti atskirai",
  "replaceModel": "Pakeisti modelį",
  "runNMS": "Be didžiausių reikšmių slopinimo (NMS)"
}
