{
  "classValueField": "Поле значений класса",
  "confidenceScoreField": "Поле балла достоверности",
  "detectObjectsInputSectionText": "Выберите слой изображений или векторный слой с вложениями изображений.",
  "detectObjectsResultSectionText": "Выходной слой объектов с обнаруженными объектами.",
  "inputRaster": "Входной слой изображений или векторный слой",
  "itemProperties": {
    "description": "Выходные данные от запуска инструмента анализа Выявить объекты при помощи глубокого обучения.",
    "snippet": "Выходные данные от Выявить объекты при помощи глубокого обучения"
  },
  "maxOverlapRatio": "Максимальный коэффициент перекрытия",
  "model": "Модель для выявления объектов",
  "modelArguments": "Аргументы модели",
  "modelLabel": "Выбрать модель",
  "processAllRasterItems": "Режим обработки",
  "processAsMosaickedImage": "Обработка как мозаики изображений",
  "processItemsSeparately": "Обрабатывать все растры отдельно",
  "replaceModel": "Заменить модель",
  "runNMS": "Не максимальное подавление (NMS)"
}
