{
  "areaUnitsLabel": "Areaenheter",
  "auto": "Baserat på indata",
  "autoSelectionMethod": "Baserat på antal regioner",
  "circle": "Cirkel",
  "combinatorial": "Kombinatorisk",
  "distanceUnitsLabel": "Distansenheter",
  "eight": "Åtta",
  "ellipse": "Ellips",
  "evaluationCriteriaSectionLabel": "Utvärderingskriterier",
  "evaluationMethodLabel": "Utvärderingsmetod",
  "four": "Fyra",
  "greatestCoreArea": "Största kärnområde",
  "greatestEdge": "Största kant",
  "hexagon": "Hexagon",
  "high": "Hög",
  "highestAverageValue": "Högsta medelvärde",
  "highestCoreSum": "Högsta summa av kärnverktygsvärden",
  "highestMedianValue": "Högsta medianvärde",
  "highestSum": "Högsta summa",
  "highestValue": "Högsta värde",
  "inExistingRegionsLabel": "Indataraster eller geoobjekt för befintliga regioner",
  "inputLayersGroupText": "Välj det indataraster som regionerna ska härledas från och identifiera regioner som redan finns.",
  "inputRasterLabel": "Indataraster",
  "itemProperties": {
    "description": "Utdata har genererats genom körning av analysverktyget Hitta regioner.",
    "snippet": "Utdata har genererats från Hitta regioner"
  },
  "large": "Stor",
  "locateSettingsGroupLabel": "Lokaliseringsinställningar",
  "locateSettingsGroupText": "Definiera totalt område, områdesenheter och antal regioner. Definiera utvärderingskriterier, regionkrav och specifikationer för regionstillväxt.",
  "low": "Låg",
  "lowestValue": "Lägsta värde",
  "maximumAreaLabel": "Maximalt område för region",
  "maximumDistanceLabel": "Maximalt avstånd mellan regioner",
  "minimumAreaLabel": "Minsta område för region",
  "minimumDistanceLabel": "Minsta avstånd mellan regioner",
  "noIslandsLabel": "Öar är inte tillåtet i regioner",
  "numberOfNeighborsLabel": "Antal grannar som ska användas i tillväxt",
  "numberOfRegionsLabel": "Antal regioner",
  "octagon": "Oktagon",
  "optionalRegionsLayerSectionLabel": "Valfritt regionslager",
  "pentagon": "Femhörning",
  "regionGrowthSpecificationsSectionLabel": "Specifikationer för regionstillväxt",
  "regionOrientationLabel": "Regionsorientering",
  "regionRequirementsSectionLabel": "Regionskrav",
  "regionResolutionLabel": "Upplösning för tillväxt",
  "regionSeedsLabel": "Antal seeds för tillväxt från",
  "regionShapeLabel": "Regionsform",
  "resolutionOfGrowthLabel": "Upplösning för tillväxt",
  "selectionMethodLabel": "Urvalsmetod för region",
  "sequential": "Sekventiell",
  "shapeTradeoffLabel": "Form/kompromiss för infrastruktur (%)",
  "small": "Liten",
  "square": "Kvadrat",
  "totalAreaLabel": "Totalyta",
  "triangle": "Liksidig triangel"
}
