{
  "countFieldLabel": "Polje populacije",
  "inBarriersLabel": "Geoobjekti ulazne barijere",
  "inputDensitySettingsGroupLabel": "Postavke za analizu gustine",
  "inputDensitySettingsGroupText": "Odredite veličinu ćelije, udaljenost pretrage i jedinice površine za analizu.",
  "inputLayersGroupText": "Izaberite ulazne karakteristike za koje ćete izračunati gustinu.",
  "inputPointOrLineFeaturesLabel": "Ulazni tačkasti ili linijski geoobjekti",
  "itemProperties": {
    "description": "Izlaz generisan pokretanjem alatke za analizu funkcije Raster za izračunavanje gustine.",
    "snippet": "Izlaz generisan iz funkcije Izračunaj gustinu"
  },
  "outputAreaUnitsLabel": "Jedinice površine",
  "outputAreaUnitsText": "Selektujte jedinicu oblasti za izračunavanje gustine...",
  "outputCellSizeLabel": "Veličina izlazne ćelije",
  "outputValueText": "Unesite vrednost...",
  "searchDistanceLabel": "Rastojanje pretrage"
}
