{
  "ImageNavigator": {
    "paginationLabel": "${n} sur ${m}",
    "noImage": "Aucune photo actuellement enregistrée avec ce site",
    "previewNotAvailable": "L’aperçu n’est pas disponible"
  },
  "PageNavigator": {
    "currentPageOutOfN": "Page ${current} sur ${total}"
  },
  "PanoramicViewer": {
    "image-viewer-close": "Fermer",
    "image-viewer-fullscreen": "Plein écran",
    "image-viewer-minimize": "Réduire",
    "image-viewer-title": "Visionneuse de photo",
    "image-viewer-show-caption": "Afficher la légende",
    "image-viewer-hide-caption": "Masquer"
  },
  "TextBox": {
    "error_numberExpected": "Un nombre est attendu",
    "error_range": "Valeur attendue comprise entre ${0} et ${1}"
  }
}