{
  "ImageNavigator": {
    "paginationLabel": "${n}/${m}",
    "noImage": "Jelenleg nincsenek képek mentve az oldalhoz",
    "previewNotAvailable": "Előnézet nem áll rendelkezésre"
  },
  "PageNavigator": {
    "currentPageOutOfN": "${current}. oldal, összesen: ${total}"
  },
  "PanoramicViewer": {
    "image-viewer-close": "Bezárás",
    "image-viewer-fullscreen": "Teljes képernyő",
    "image-viewer-minimize": "Minimális méret",
    "image-viewer-title": "Fényképnézegető",
    "image-viewer-show-caption": "Képaláírás megjelenítése",
    "image-viewer-hide-caption": "Elrejtés"
  },
  "TextBox": {
    "error_numberExpected": "Számot kell megadni",
    "error_range": "Várható érték: ${0} – ${1}"
  }
}