{
  "andOperatorLabel": "Es compleixen totes les condicions següents",
  "attributeExpression": "Expressió d'atributs",
  "choiceList": "Llista d'opcions",
  "dateUnits": {
    "days": "dies",
    "hours": "hores",
    "minutes": "minuts",
    "months": "mesos",
    "weeks": "setmanes",
    "years": "anys"
  },
  "error": "Error",
  "errorRetrievingFieldValues": "No s'han pogut recuperar els valors de camp.‎",
  "expression": "Expressió",
  "expressionDateUnitSelect": "Seleccioneu una data",
  "expressionGroup": "Grup d'expressions",
  "expressionOperatorSelect": "Seleccioneu l'operador d'expressió",
  "false": "Fals",
  "fieldSelect": "Selecció de camps",
  "genericError": "S'ha produït un error en pujar el generador de consultes.",
  "groupOperatorSelect": "Seleccioneu l'operador de grup d'expressions",
  "inputPlaceholderText": "Introduïu el valor...",
  "invalidExpression": "L'expressió no és vàlida.",
  "invalidExpressionGroup": "El grup d'expressions no és vàlid.",
  "invalidSpatialExpression": "L'expressió espacial no és vàlida.",
  "layersLoadError": "No s'han pogut pujar les capes.",
  "loading": "S'està carregant...",
  "loadingFieldValues": "S'estan carregant valors...",
  "multiInputPlaceholderText": "Introduïu els valors...‎",
  "noCompatibleLayers": "(no hi ha cap capa compatible)",
  "noFieldValuesRetrieved": "No s'ha pogut recuperar cap valor per a aquest camp.",
  "operators": {
    "begins_with": "comença per",
    "between": "és entre",
    "contains": "conté",
    "ends_with": "acaba per",
    "equal": "és",
    "greater": "és major que",
    "greater_or_equal": "és com a mínim",
    "in_the_last": "a l'últim",
    "is_after": "està després de",
    "is_before": "està abans de",
    "is_blank": "està en blanc",
    "is_empty": "és una cadena buida",
    "is_false": "és fals",
    "is_in": "és a",
    "is_not_blank": "no està en blanc",
    "is_not_empty": "no és una cadena buida",
    "is_not_in": "no és a",
    "is_not_on": "no és a",
    "is_on": "és a",
    "is_true": "és cert",
    "less": "és més menor que",
    "less_or_equal": "és com a màxim",
    "not_begins_with": "no comença per",
    "not_between": "no està entre",
    "not_contains": "no conté",
    "not_ends_with": "no acaba per",
    "not_equal": "no és",
    "not_in_the_last": "no és al darrer"
  },
  "orOperatorLabel": "Es compleix una de les condicions següents",
  "parsingPreviousQueryError": "S'ha produït un error en analitzar la consulta anterior.",
  "queryFieldsError": "La consulta utilitza camps que no existeixen.",
  "removeAttributeExpression": "Elimina l'expressió",
  "removeExpressionGroup": "Elimina el grup d'expressions",
  "spatialExpression": "Expressió espacial",
  "spatialExpressionTwoLayers": "Les expressions espacials necessiten com a mínim dues capes diferents.",
  "spatialRelationshipLayerSelect": "Selecció de capes de relacions espacials",
  "spatialRelationshipParamsDistanceInput": "Entrada de distància de relació espacial",
  "spatialRelationshipSelect": "Selecció de relacions espacials",
  "spatialRelationshipUnits": {
    "Feet": "Peus",
    "Kilometers": "Quilòmetres",
    "Meters": "Metres",
    "Miles": "Milles",
    "Yards": "Iardes"
  },
  "spatialRelationships": {
    "contains": "Conté completament ${noCompatibleLayers}",
    "intersects": "S'interseca amb ${noCompatibleLayers}",
    "nearest": "Més proper a ${noCompatibleLayers}",
    "notContains": "No conté completament ${noCompatibleLayers}",
    "notIntersects": "No s'interseca amb ${noCompatibleLayers}",
    "notWithin": "No és completament dins de ${noCompatibleLayers}",
    "notWithinDistance": "No és dins d'una distància de ${noCompatibleLayers}",
    "within": "Completament dins de ${noCompatibleLayers}",
    "withinDistance": "Dins d'una distància de ${noCompatibleLayers}"
  },
  "targetDatasetLoadError": "No s'ha pogut pujar el dataset.",
  "tooManyValuesToDisplay": "Hi ha massa valors per mostrar.",
  "true": "Cert",
  "where": "On"
}
