{
  "addFile": "Pridėti failą",
  "itemNotFound": "Elementas neegzistuoja arba yra nepasiekiamas.",
  "itemPermissionDenied": "Neturite teisės pasiekti šio elemento.",
  "queryModelArgsErrMsg": "Nepavyko pateikti modelio argumentų užklausos.",
  "queryModelArgsMsg": "Teikiama užklausa dėl modelio argumentų...",
  "removeItem": "Pašalinti elementą",
  "replaceItem": "Keisti elementą",
  "requiredInputMessage": "Šis parametras yra būtinas.",
  "selectItem": "Pasirinkti elementą",
  "selectModel": "Pasirinkti modelį"
}
