{
  "allowAnalysisReason": "Satu atau lebih layer dari peta tidak terdaftar di sini karena ini tidak mengizinkan analisis. <a href='${ docLink }' target='_blank'>Pelajari selengkapnya.</a><br>",
  "featureCountAboveMaximum": "Hitungan fitur tidak boleh lebih besar dari ${maximum}.",
  "featureCountBelowMinimum": "Hitungan fitur tidak boleh kurang dari ${minimum}.",
  "isRequired": "Parameter ini harus diisi",
  "layer": "Layer",
  "layerAction": "${layerName} tindakan",
  "layerNotAvailable": "Gagal memuat layer ${layerName}",
  "layerNotSupported": "Layer yang dipilih tidak didukung.",
  "layersFilteredOut": "Beberap layer telah difilter.",
  "layersNotAllowAnalysis": "Analisis tidak diizinkan untuk beberapa layer di peta ini.",
  "multipleLayersNotAvailable": "Gagal memuat layer ${layerName} dan lainnya",
  "numberFeatures": "Jumlah fitur: ${featureCount}",
  "numberFeaturesLoading": "Menghitung...",
  "proxyReason": "Satu atau lebih layer dari peta tidak terdaftar di sini karena mereka tidak didukung untuk analisis. <a href='${ docLink }' target='_blank'>Pelajari selengkapnya.</a><br>",
  "replaceLayer": "Ganti layer"
}
