{
  "attributeRelationship": "Atribútové väzby",
  "calculateStatistics": "Sumarizovať zhodné záznamy",
  "equal": "Rovná sa",
  "handleMatchingRecords": "Viacero zhodných záznamov",
  "innerJoin": "Vnútorné pripojenie",
  "itemProperties": {
    "description": "Výstup vygenerovaný spustením nástroja Pripojiť prvky.",
    "snippet": "Výstup vygenerovaný z Pripojiť prvky"
  },
  "joinField": "Pole na pripojenie",
  "joinInputSummaryText": "Vyberte prvkové alebo tabuľkové vrstvy na pripojenie.",
  "joinLayer": "Vrstvu pripojenia",
  "joinOneToMany": "Pripojiť jeden s viacerými",
  "joinOneToOne": "Pripojiť jeden s jedným",
  "joinOperation": "Operácia pripojenia",
  "joinSettings": "Nastavenia pripojenia",
  "joinSettingsSummaryText": "Špecifikujte väzbu medzi vstupmi a ktoré záznamy budú vrátené.",
  "joinType": "Typ pripojenia",
  "largest": "Najväčšie",
  "leftJoin": "Ľavé pripojenie",
  "newest": "Najnovšie",
  "oldest": "Najstaršie",
  "operator": "Operátor",
  "orderRecords": "Zoradiť podľa",
  "orderType": "Hodnota",
  "smallest": "Najmenšie",
  "sortOrderLabel": "Poradie zoradenia",
  "spatialRelationship": "Priestorový vzťah",
  "targetField": "Cieľové pole",
  "targetLayer": "Cieľová vrstva",
  "topMatchingRecord": "Ponechať len prvý zhodný záznam",
  "useAttributeRelationship": "Použiť atribútovú väzbu",
  "useSpatialRelationship": "Použiť priestorový vzťah"
}
