{
  "inputInterpolationSettingGroupLabel": "插值设置",
  "inputInterpolationSettingGroupText": "指定精度、插值的局部模型和输出的分辨率。",
  "inputLayerGroupText": "选择要插值的字段和位置的要素图层。",
  "inputPointFeatureLabel": "输入点要素",
  "interpolateFieldLabel": "插值字段",
  "itemProperties": {
    "description": "通过运行“插值点栅格”分析工具而生成的输出。",
    "snippet": "通过插值点栅格生成的输出"
  },
  "numberOfRegionsLabel": "相邻要素的数目",
  "optimizeForLabel": "优化",
  "optionsLabel": "选项",
  "outputCellSizeLabel": "输出像元大小",
  "outputPredictionErrorLabel": "创建预测标准误差栅格",
  "outputRasterLabel": "输出栅格名称",
  "outputValueText": "输入值...",
  "sizeOfLocalModelsLabel": "局部模型的大小",
  "transformDataLabel": "转换数据"
}
