{
  "demResolution": "רזולוציה",
  "generalize": "הכלל",
  "inputLayerGroupText": "בחר שכבת ישויות נקודה המייצגות מיקומים של צופה.",
  "inputObserverFeaturesLayerLabel": "קלט שכבת ישויות צופה",
  "inputViewshedSettingGroupLabel": "הגדרות קווי ראייה",
  "inputViewshedSettingGroupText": "ציין את הגדרות הצופה והיעד לניתוח קו ראייה.",
  "itemProperties": {
    "description": "פלט הופק מהרצת כלי ניתוח יצירת שדה ראייה.",
    "snippet": "פלט הופק מיצירת קו ראייה"
  },
  "maximumViewingDistanceLabel": "מרחק צפייה מקסימלי",
  "observerHeightUnitLabel": "יחידות גובה צופה",
  "observersHeightLabel": "גובה צופה",
  "outputPolygonNameLabel": "שם פוליגון פלט",
  "targetHeightLabel": "גובה יעד",
  "targetHeightUnitLabel": "יחידות גובה יעד",
  "viewingDistanceUnitLabel": "יחידות מרחק צפייה"
}
