{
  "distanceFieldLabel": "Vahemaa väli",
  "distanceLabel": "Vahemaa",
  "inputElevationSurfaceLabel": "Sisendkõrguspind",
  "inputLayersGroupText": "Valige kõrgusrastri sisendkiht ja vaatlemisasukohtade sisendobjektikiht.",
  "inputObserverFeatureLabel": "Sisendvaatluspunkti või jooneobjektid",
  "inputViewshedSettingsGroupLabel": "Vaatevälja seaded",
  "inputViewshedSettingsGroupText": "Saate määrata parameetrid, mis juhivad vaatevälja analüüsi.",
  "itemProperties": {
    "description": "Analüüsitööriista Geodeetiline vaateväli käitamise kaudu loodud väljund.",
    "snippet": "Lahenduse Geodeetiline vaateväli kaudu loodud väljund"
  },
  "linearUnitLabel": "Väärtus",
  "linearUnitText": "Sisestage väärtus...",
  "maximumViewingDistanceGroupLabel": "Suurim vaatamiskaugus",
  "minimumViewingDistanceGroupLabel": "Väikseim vaatamiskaugus",
  "observerparametersLabel": "Vaatleja parameetrid",
  "observersElevationFieldLabel": "Kõrgusandmete väli",
  "observersElevationGroupLabel": "Vaatleja asukohtade kõrgus",
  "observersElevationLabel": "Kõrgusandmed",
  "observersHeightFieldLabel": "Kõrguse väli",
  "observersHeightGroupLabel": "Vaatleja kõrgus",
  "observersHeightLabel": "Kõrgus",
  "optimizeForLabel": "Optimeeri järgmise jaoks",
  "outputAboveGroundLevelRasterNameLabel": "Maapinnast kõrgema taseme väljundrastri nimi",
  "outputViewshedRasterNameLabel": "Vaatevälja väljundrastri nimi",
  "targetHeightFieldLabel": "Kõrguse väli",
  "targetHeightGroupLabel": "Sihtmärgi kõrgus",
  "targetHeightLabel": "Kõrgus",
  "viewingDistanceIs3DLabel": "Vaatamiskaugus on 3D"
}
