{
  "analysisLayerLabel": "Camada de entrada",
  "inputLayersSummaryText": "Localizar as feições mais próximas da camada de Proximidade para cada feição na camada de entrada. Opcionalmente, selecione camadas de barreira para restringir viagens em determinadas áreas quando a análise usar um modo de viagem.",
  "itemProperties": {
    "description": "Camada de feição gerada a partir da execução da ferramenta de análise Localizar Mais Próximo.",
    "snippet": "Camada de feição gerada a partir de Localizar Mais Próximo"
  },
  "limitNearNumberLabel": "Limite o número de locais mais próximos",
  "limitSearchRangeLabel": "Limitar o intervalo de pesquisa",
  "maxCountLabel": "Número máximo de locais mais próximos a serem encontrados por entrada",
  "maxSearchRangeLabel": "Intervalo máximo de pesquisa",
  "maxSearchRangeTimeLabel": "Alcance máximo de pesquisa (minutos)",
  "maxSearchRangeUnitLabel": "Unidades de intervalo de pesquisa",
  "nearLayerLabel": "Camada de proximidade"
}
