{
  "analysisLayerLabel": "Eingabe-Layer",
  "inputLayersSummaryText": "Für jedes Feature im Eingabe-Layer die nächstgelegenen Features aus dem Near-Layer suchen. Wählen Sie optional Barriere-Layer aus, um das Reisen in bestimmte Gebiete einzuschränken, wenn die Analyse einen Reisemodus verwendet.",
  "itemProperties": {
    "description": "Durch Ausführung des Analysewerkzeugs \"Nächstgelegene suchen\" generierter Feature-Layer.",
    "snippet": "Über \"Nächstgelegene suchen\" generierter Feature-Layer"
  },
  "limitNearNumberLabel": "Anzahl der nächstgelegenen Positionen begrenzen",
  "limitSearchRangeLabel": "Suchbereich begrenzen",
  "maxCountLabel": "Maximale Anzahl der zu suchenden nächstgelegenen Positionen pro Eingabe",
  "maxSearchRangeLabel": "Maximaler Suchbereich",
  "maxSearchRangeTimeLabel": "Maximaler Suchbereich (Minuten)",
  "maxSearchRangeUnitLabel": "Einheiten für Suchbereich",
  "nearLayerLabel": "Near-Layer"
}
