{
  "inPourPointRasterOrFeaturesLabel": "Ráster o entidades de puntos de fluidez de entrada",
  "inputFlowDirectionRasterLabel": "Ráster de dirección del flujo de entrada",
  "inputLayersGroupText": "Elija la capa de dirección del flujo y la capa de puntos de fluidez para crear una cuenca hidrográfica en la ubicación de los puntos de fluidez.",
  "itemProperties": {
    "description": "Salida generada al ejecutar la herramienta de análisis Cuenca hidrográfica.",
    "snippet": "Salida generada a partir de Cuenca hidrográfica"
  },
  "pourPointFieldLabel": "Campo de punto de fluidez",
  "resultType": "Tipo de capa de salida"
}
