{
  "inputConversionSettingsGroupLabel": "Paramètres de conversion",
  "inputConversionSettingsGroupText": "Sélectionner le champ qui attribue des valeurs aux cellules en sortie. Spécifier la taille de cellule en sortie.",
  "inputFeatureLabel": "Couche d’entités en entrée",
  "inputLayerGroupText": "Sélectionner la couche d’entités à convertir en raster.",
  "itemProperties": {
    "description": "Sortie générée en exécutant l’outil d’analyse Convertir l’entité en raster.",
    "snippet": "Sortie générée avec Convertir l’entité en raster"
  },
  "outputCellSizeLabel": "Taille de cellule en sortie",
  "outputCellSizeText": "Saisir une valeur...",
  "valueFieldLabel": "Champ de valeur"
}
