{
  "aggregationDefinition": "Definicija grupisanja",
  "aggregationFunction": "Prilagođena funkcija grupisanja",
  "aggregationMethod": "Metoda grupisanja",
  "custom": "Prilagođeno",
  "dekadly": "Dekadno",
  "dimension": "Dimenzija",
  "dimensionLabel": "Izaberite dimenziju iz sloja...",
  "dimensionless": "Bez dimenzije",
  "inputMultidimensionalRaster": "Višedimenzionalni sloj snimaka",
  "intervalKeyword": "Interval ključne reči",
  "intervalRanges": "Opsezi intervala",
  "intervalUnit": "Jedinica intervala",
  "intervalValue": "Vrednost intervala",
  "intervalValuePlaceholder": "Unesite vrednost intervala",
  "itemProperties": {
    "description": "Izlaz generisan pokretanjem alatke za analizu funkcije Agregatni višedimenzionalni raster.",
    "snippet": "Izlaz generisan iz funkcije Agregatni multidimenzionalni raster"
  },
  "linear": "Linearno",
  "maxValue": "Maksimalna vrednost",
  "maxValuePlaceholder": "Unesite maksimalnu vrednost",
  "minValue": "Minimalna vrednost",
  "minValuePlaceholder": "Unesite minimalnu vrednost",
  "nearest": "Najbliži",
  "pentadly": "Pentadno",
  "percentileInterpolationType": "Tip percentilne interpolacije",
  "percentileValue": "Percentilna vrednost",
  "selectVariables": "Selektujte promenljive",
  "settingsGroupLabel": "Postavke grupisanja",
  "variables": "Promenljive [informacije o dimenziji] (opis)"
}
