{
  "aggregationDefinition": "Дефиниция за обобщаване",
  "aggregationFunction": "Персонализирана функция за обобщаване",
  "aggregationMethod": "Метод на обобщаване",
  "custom": "Персонализиран",
  "dekadly": "Декадлично",
  "dimension": "Размер",
  "dimensionLabel": "Изберете размер от слой...",
  "dimensionless": "Безразмерни",
  "inputMultidimensionalRaster": "Многоизмерен слой изображения",
  "intervalKeyword": "Интервал на ключова дума",
  "intervalRanges": "Диапазони на интервал",
  "intervalUnit": "Интервална единица",
  "intervalValue": "Стойност на интервал",
  "intervalValuePlaceholder": "Въвеждане на стойност на интервал",
  "itemProperties": {
    "description": "Резултат, генериран от изпълнението на инструмента за анализ Обобщен многоизмерен растер.",
    "snippet": "Резултат, генериран от Обобщен многоизмерен растер"
  },
  "linear": "Линейна",
  "maxValue": "Максимална стойност",
  "maxValuePlaceholder": "Въвеждане на максимална стойност",
  "minValue": "Минимална стойност",
  "minValuePlaceholder": "Въвеждане на минимална стойност",
  "nearest": "Най-близка",
  "pentadly": "Пентадли",
  "percentileInterpolationType": "Тип перцентилна интерполация",
  "percentileValue": "Перцентилна стойност",
  "selectVariables": "Изберете променливи",
  "settingsGroupLabel": "Настройки на обобщаване",
  "variables": "Променливи [информация за размерите] (описание)"
}
