{
  "distancesLabel": "Vrednosti meritve",
  "itemProperties": {
    "description": "Geoobjektni sloj, ustvarjen z izvajanjem orodja za analizo Povzemi v bližini.",
    "snippet": "Geoobjektni sloj, ustvarjen iz Povzemi v bližini"
  },
  "nearTypeLabel": "Tip meritve",
  "returnFeatureCollectionLabel": "Shrani kot začasno zbirko geoobjektov",
  "sumNearbyLayerLabel": "Sloj v bližini",
  "summaryAreasSectionLabel": "Omejitvena območja v bližini",
  "summaryAreasSectionText": "Izberite sloj, okoli katerega bodo ustvarjena omejitvena območja."
}
